tools/__init__.py
tools/demo.py
tools/eval.py
tools/export_onnx.py
tools/export_torchscript.py
tools/train.py
tools/trt.py
yolox/_C.cpython-36m-x86_64-linux-gnu.so
yolox/__init__.py
yolox/core/__init__.py
yolox/core/launch.py
yolox/core/trainer.py
yolox/data/__init__.py
yolox/data/data_augment.py
yolox/data/data_prefetcher.py
yolox/data/dataloading.py
yolox/data/samplers.py
yolox/data/datasets/__init__.py
yolox/data/datasets/coco.py
yolox/data/datasets/coco_classes.py
yolox/data/datasets/datasets_wrapper.py
yolox/data/datasets/mosaicdetection.py
yolox/data/datasets/voc.py
yolox/data/datasets/voc_classes.py
yolox/evaluators/__init__.py
yolox/evaluators/coco_evaluator.py
yolox/evaluators/voc_eval.py
yolox/evaluators/voc_evaluator.py
yolox/exp/__init__.py
yolox/exp/base_exp.py
yolox/exp/build.py
yolox/exp/yolox_base.py
yolox/exp/default/__init__.py
yolox/exp/default/yolov3.py
yolox/exp/default/yolox_l.py
yolox/exp/default/yolox_m.py
yolox/exp/default/yolox_nano.py
yolox/exp/default/yolox_s.py
yolox/exp/default/yolox_tiny.py
yolox/exp/default/yolox_x.py
yolox/layers/__init__.py
yolox/layers/fast_coco_eval_api.py
yolox/models/__init__.py
yolox/models/darknet.py
yolox/models/losses.py
yolox/models/network_blocks.py
yolox/models/yolo_fpn.py
yolox/models/yolo_head.py
yolox/models/yolo_pafpn.py
yolox/models/yolox.py
yolox/tools/__init__.py
yolox/tools/demo.py
yolox/tools/eval.py
yolox/tools/export_onnx.py
yolox/tools/export_torchscript.py
yolox/tools/train.py
yolox/tools/trt.py
yolox/utils/__init__.py
yolox/utils/allreduce_norm.py
yolox/utils/boxes.py
yolox/utils/checkpoint.py
yolox/utils/demo_utils.py
yolox/utils/dist.py
yolox/utils/ema.py
yolox/utils/logger.py
yolox/utils/lr_scheduler.py
yolox/utils/metric.py
yolox/utils/model_utils.py
yolox/utils/setup_env.py
yolox/utils/visualize.py
yolox-0.2.0.dist-info/LICENSE
yolox-0.2.0.dist-info/METADATA
yolox-0.2.0.dist-info/WHEEL
yolox-0.2.0.dist-info/top_level.txt
yolox-0.2.0.dist-info/RECORD
