Metadata-Version: 2.1
Name: yolox
Version: 0.2.0
Summary: UNKNOWN
Home-page: https://github.com/Megvii-BaseDetection/YOLOX
Author: megvii basedet team
License: UNKNOWN
Project-URL: Documentation, https://yolox.readthedocs.io
Project-URL: Source, https://github.com/Megvii-BaseDetection/YOLOX
Project-URL: Tracker, https://github.com/Megvii-BaseDetection/YOLOX/issues
Platform: UNKNOWN
Classifier: Programming Language :: Python :: 3
Classifier: Operating System :: OS Independent
Classifier: License :: OSI Approved :: Apache Software License
Requires-Python: >=3.6
License-File: LICENSE
Requires-Dist: numpy
Requires-Dist: torch (>=1.7)
Requires-Dist: opencv-python
Requires-Dist: loguru
Requires-Dist: scikit-image
Requires-Dist: tqdm
Requires-Dist: torchvision
Requires-Dist: Pillow
Requires-Dist: thop
Requires-Dist: ninja
Requires-Dist: tabulate
Requires-Dist: tensorboard
Requires-Dist: pycocotools (>=2.0.2)
Requires-Dist: onnx (==1.8.1)
Requires-Dist: onnxruntime (==1.8.0)
Requires-Dist: onnx-simplifier (==0.3.5)
